__init__.py
VisualizePhonon/__init__.py
VisualizePhonon/cmdline.py
VisualizePhonon/vibrational_analysis.py
VisualizePhonon/vibrational_analysis_io.py
visualizephonon-0.0.2.dist-info/METADATA
visualizephonon-0.0.2.dist-info/WHEEL
visualizephonon-0.0.2.dist-info/entry_points.txt
visualizephonon-0.0.2.dist-info/top_level.txt
visualizephonon-0.0.2.dist-info/RECORD
